example/__init__.py
example/__main__.py
example/third_party.py
example/data/__init__.py
example/data/aws/__init__.py
example/data/aws/reader.py
example/data/azure/__init__.py
example/data/azure/reader.py
example/models/__init__.py
example/models/simple.py
pyinject3/__init__.py
pyinject3/_version.py
pyinject3/registrar.py
pyinject3/yaml_config.py
type_registry/__init__.py
type_registry/_version.py
type_registry/registrar.py
type_registry/yaml_config.py
type_registry-1.2.dist-info/LICENSE
type_registry-1.2.dist-info/METADATA
type_registry-1.2.dist-info/WHEEL
type_registry-1.2.dist-info/top_level.txt
type_registry-1.2.dist-info/RECORD
